README.md
setup.py
kegbot/__init__.py
kegbot/util/__init__.py
kegbot/util/app.py
kegbot/util/units.py
kegbot/util/units_test.py
kegbot/util/util.py
kegbot/util/util_test.py
kegbot_pyutils.egg-info/PKG-INFO
kegbot_pyutils.egg-info/SOURCES.txt
kegbot_pyutils.egg-info/dependency_links.txt
kegbot_pyutils.egg-info/namespace_packages.txt
kegbot_pyutils.egg-info/requires.txt
kegbot_pyutils.egg-info/top_level.txt