Metadata-Version: 2.1
Name: kegbot-pyutils
Version: 1.0.0
Summary: Python utilities used in the Kegbot Project
Home-page: https://kegbot.org/
Author: The Kegbot Project Contributors
Author-email: info@kegbot.org
License: MIT
Platform: UNKNOWN
